Metadata-Version: 1.1
Name: tally
Version: 1.0.0
Summary: A Django application (and daemon) for collecting, storing, and aggregating metrics.
Home-page: https://github.com/dcwatson/tally
Author: Dan Watson
Author-email: dcwatson@gmail.com
License: BSD
Platform: UNKNOWN
Classifier: Development Status :: 3 - Alpha
Classifier: Intended Audience :: Developers
Classifier: License :: OSI Approved :: BSD License
Classifier: Operating System :: OS Independent
Classifier: Programming Language :: Python
Classifier: Topic :: Utilities
